MANIFEST.in
README.md
setup.py
ct_tools/__init__.py
ct_tools.egg-info/PKG-INFO
ct_tools.egg-info/SOURCES.txt
ct_tools.egg-info/dependency_links.txt
ct_tools.egg-info/requires.txt
ct_tools.egg-info/top_level.txt
ct_tools/common_utils/__init__.py
ct_tools/django_utils/__init__.py
ct_tools/django_utils/cache/__init__.py
ct_tools/django_utils/exception/__init__.py
ct_tools/django_utils/exception/capture_exception.py
ct_tools/django_utils/logger/__init__.py
ct_tools/django_utils/logger/test.py
ct_tools/django_utils/management/__init__.py
ct_tools/django_utils/management/commands/__init__.py
ct_tools/django_utils/management/commands/data2file.py
ct_tools/django_utils/middlewares/__init__.py
ct_tools/django_utils/middlewares/corsmiddleware.py
ct_tools/django_utils/middlewares/exceptionmiddleware.py
ct_tools/django_utils/middlewares/localmiddleware.py
ct_tools/django_utils/models/DjangoBaseModel.py
ct_tools/django_utils/models/DynamicUtil.py
ct_tools/django_utils/models/__init__.py
ct_tools/django_utils/pinyin/__init__.py
ct_tools/django_utils/pinyin/files/Mandarin.dat
ct_tools/django_utils/requests/__init__.py
ct_tools/django_utils/responses/__init__.py
ct_tools/django_utils/utils/__init__.py
ct_tools/django_utils/utils/file_handle.py
ct_tools/django_utils/utils/number_tools.py
ct_tools/django_utils/utils/timing.py
ct_tools/django_utils/utils/excel_tools/__init__.py
ct_tools/django_utils/utils/excel_tools/loader.py
ct_tools/django_utils/utils/excel_tools/loader_test.py
ct_tools/django_utils/utils/login_tools/__init__.py
ct_tools/django_utils/utils/login_tools/_login_required.py
ct_tools/django_utils/views/__init__.py
ct_tools/django_utils/views/httpbaseview1.py
ct_tools/django_utils/views/httpbaseview2.py
ct_tools/django_utils/views/test.py
ct_tools/excel_utils/__init__.py
ct_tools/mysqldb/PyMysqlClient.py
ct_tools/mysqldb/__init__.py